ntlm/HTTPNtlmAuthHandler.py
ntlm/U32.py
ntlm/__init__.py
ntlm/des.py
ntlm/des_c.py
ntlm/des_data.py
ntlm/ntlm.py
urllib_ntlm-0.1.1.dist-info/WHEEL
urllib_ntlm-0.1.1.dist-info/METADATA
urllib_ntlm-0.1.1.dist-info/RECORD
