Metadata-Version: 2.1
Name: urllib-ntlm
Version: 0.1.1
Summary: NTLM Authenticator for urllib.request
Home-page: https://github.com/mortbauer/urllib-ntlm
License: MIT
Author: Martin Ortbauer
Author-email: mortbauer@gmail.com
Requires-Python: >=3.7,<4.0
Classifier: License :: OSI Approved :: MIT License
Classifier: Programming Language :: Python :: 3
Classifier: Programming Language :: Python :: 3.10
Classifier: Programming Language :: Python :: 3.7
Classifier: Programming Language :: Python :: 3.8
Classifier: Programming Language :: Python :: 3.9
